python_http_parser/__init__.py
python_http_parser/__init__.pyi
python_http_parser/body.py
python_http_parser/bytedata.py
python_http_parser/constants.py
python_http_parser/constants.pyi
python_http_parser/errors.py
python_http_parser/stream.py
python_http_parser/utils.py
python_http_parser/utils.pyi
python_http_parser/helpers/__init__.py
python_http_parser/helpers/events.py
python_http_parser/helpers/newline.py
python_http_parser-0.4.3.dist-info/LICENSE
python_http_parser-0.4.3.dist-info/METADATA
python_http_parser-0.4.3.dist-info/WHEEL
python_http_parser-0.4.3.dist-info/top_level.txt
python_http_parser-0.4.3.dist-info/RECORD
