Metadata-Version: 2.1
Name: python-http-parser
Version: 0.4.3
Summary: HTTP parser and stringifier written in pure python.
Home-page: https://github.com/Take-Some-Bytes/python_http_parser
Author: Take-Some-Bytes
Author-email: horton0712@gmail.com
License: MIT License
Project-URL: Documentation, https://python-http-parser.readthedocs.io/en/latest/
Project-URL: Bugs, https://github.com/Take-Some-Bytes/python_http_parser/issues
Platform: UNKNOWN
Classifier: Development Status :: 2 - Pre-Alpha
Classifier: Environment :: Web Environment
Classifier: Intended Audience :: Developers
Classifier: License :: OSI Approved :: MIT License
Classifier: Operating System :: OS Independent
Classifier: Programming Language :: Python
Classifier: Programming Language :: Python :: 3
Classifier: Programming Language :: Python :: 3 :: Only
Classifier: Programming Language :: Python :: 3.6
Classifier: Programming Language :: Python :: 3.7
Classifier: Programming Language :: Python :: 3.8
Classifier: Programming Language :: Python :: 3.9
Classifier: Topic :: Internet
Classifier: Topic :: Internet :: WWW/HTTP
Classifier: Topic :: Utilities
Classifier: Topic :: Software Development :: Libraries :: Python Modules
Requires-Python: >=3.6
License-File: LICENSE
Requires-Dist: typing-extensions
